arbs_exchanges/__init__.py
arbs_exchanges/utils.py
arbs_exchanges/adapters/__init__.py
arbs_exchanges/adapters/infra/__init__.py
arbs_exchanges/adapters/infra/bitflyer/__init__.py
arbs_exchanges/adapters/infra/bitflyer/bitflyer_order_repository.py
arbs_exchanges/adapters/infra/bitflyer/bitflyer_rest_repository.py
arbs_exchanges/adapters/infra/bitflyer/bitflyer_ws_repository.py
arbs_exchanges/adapters/infra/bybit/__init__.py
arbs_exchanges/adapters/infra/bybit/bybit_order_link_id_generator.py
arbs_exchanges/adapters/infra/bybit/bybit_order_repository.py
arbs_exchanges/adapters/infra/bybit/bybit_rest_repository.py
arbs_exchanges/adapters/infra/bybit/bybit_sizer.py
arbs_exchanges/adapters/infra/bybit/bybit_ws_repository.py
arbs_exchanges/adapters/infra/oanda/__init__.py
arbs_exchanges/adapters/infra/oanda/mt5_interface.py
arbs_exchanges/adapters/infra/oanda/oanda_order_repository.py
arbs_exchanges/adapters/infra/oanda/oanda_rest_repository.py
arbs_exchanges/adapters/infra/phemex/__init__.py
arbs_exchanges/adapters/infra/phemex/phemex_order_repository.py
arbs_exchanges/adapters/infra/phemex/phemex_rest_repository.py
arbs_exchanges/adapters/infra/phemex/phemex_ws_repository.py
arbs_exchanges/adapters/resolvers/__init__.py
arbs_exchanges/adapters/resolvers/bitflyer.py
arbs_exchanges/adapters/resolvers/bybit.py
arbs_exchanges/adapters/resolvers/phemex.py
arbs_exchanges/core/__init__.py
arbs_exchanges/core/domain/__init__.py
arbs_exchanges/core/domain/entities/__init__.py
arbs_exchanges/core/domain/entities/balance.py
arbs_exchanges/core/domain/entities/execution.py
arbs_exchanges/core/domain/entities/fee.py
arbs_exchanges/core/domain/entities/order.py
arbs_exchanges/core/domain/entities/order_book.py
arbs_exchanges/core/domain/entities/order_type.py
arbs_exchanges/core/domain/entities/position.py
arbs_exchanges/core/domain/entities/symbol.py
arbs_exchanges/core/domain/repositories/__init__.py
arbs_exchanges/core/domain/repositories/i_balance_repository.py
arbs_exchanges-0.1.2.dist-info/METADATA
arbs_exchanges-0.1.2.dist-info/WHEEL
arbs_exchanges-0.1.2.dist-info/top_level.txt
arbs_exchanges-0.1.2.dist-info/RECORD
