Metadata-Version: 2.1
Name: arbs_exchanges
Version: 0.1.2
Summary: 複数の仮想通貨取引所のREST APIとWebSocket APIのラッパー
Home-page: https://github.com/knao124/arbs_exchanges
Author: knao124
Author-email: noname@gmail.com
Classifier: Development Status :: 3 - Alpha
Classifier: Intended Audience :: Developers
Classifier: License :: OSI Approved :: MIT License
Classifier: Operating System :: OS Independent
Classifier: Programming Language :: Python :: 3
Classifier: Programming Language :: Python :: 3.7
Classifier: Programming Language :: Python :: 3.8
Classifier: Programming Language :: Python :: 3.9
Classifier: Programming Language :: Python :: 3.10
Requires-Python: >=3.7
Requires-Dist: ccxt
Requires-Dist: numpy==1.24.3
Requires-Dist: numba
Requires-Dist: pybotters
Requires-Dist: pytest
Requires-Dist: pytest-asyncio
Requires-Dist: pytest-cov
Requires-Dist: pytest-mock
Requires-Dist: python-dotenv
Requires-Dist: PyYAML
Requires-Dist: slack-sdk
Requires-Dist: yfinance
